{
  "context": {
    "date": "2026-03-31T10:51:29+08:00",
    "host_name": "typecombinator",
    "executable": "./build/release/tests/bench/balanced_tree/balanced_tree",
    "num_cpus": 4,
    "mhz_per_cpu": 2904,
    "cpu_scaling_enabled": false,
    "caches": [
      {
        "type": "Data",
        "level": 1,
        "size": 32768,
        "num_sharing": 1
      },
      {
        "type": "Instruction",
        "level": 1,
        "size": 32768,
        "num_sharing": 1
      },
      {
        "type": "Unified",
        "level": 2,
        "size": 262144,
        "num_sharing": 1
      },
      {
        "type": "Unified",
        "level": 3,
        "size": 16777216,
        "num_sharing": 4
      }
    ],
    "load_avg": [0.918945,0.885254,0.626953],
    "library_version": "v1.9.0",
    "library_build_type": "release",
    "json_schema_version": 1
  },
  "benchmarks": [
    {
      "name": "freebsd irbt,s,ordered_insert/1024",
      "family_index": 0,
      "per_family_instance_index": 0,
      "run_name": "freebsd irbt,s,ordered_insert/1024",
      "run_type": "iteration",
      "repetitions": 1,
      "repetition_index": 0,
      "threads": 1,
      "iterations": 35190,
      "real_time": 1.9667569337885438e+04,
      "cpu_time": 1.9662860358056270e+04,
      "time_unit": "ns"
    },
    {
      "name": "freebsd irbt,s,ordered_insert/2048",
      "family_index": 0,
      "per_family_instance_index": 1,
      "run_name": "freebsd irbt,s,ordered_insert/2048",
      "run_type": "iteration",
      "repetitions": 1,
      "repetition_index": 0,
      "threads": 1,
      "iterations": 16125,
      "real_time": 4.4930210294571523e+04,
      "cpu_time": 4.4924620217054246e+04,
      "time_unit": "ns"
    },
    {
      "name": "freebsd irbt,s,ordered_insert/4096",
      "family_index": 0,
      "per_family_instance_index": 2,
      "run_name": "freebsd irbt,s,ordered_insert/4096",
      "run_type": "iteration",
      "repetitions": 1,
      "repetition_index": 0,
      "threads": 1,
      "iterations": 7222,
      "real_time": 9.6832162004971833e+04,
      "cpu_time": 9.6821826363888133e+04,
      "time_unit": "ns"
    },
    {
      "name": "freebsd irbt,s,ordered_insert/8192",
      "family_index": 0,
      "per_family_instance_index": 3,
      "run_name": "freebsd irbt,s,ordered_insert/8192",
      "run_type": "iteration",
      "repetitions": 1,
      "repetition_index": 0,
      "threads": 1,
      "iterations": 3309,
      "real_time": 2.1212286672701317e+05,
      "cpu_time": 2.1210378754910859e+05,
      "time_unit": "ns"
    },
    {
      "name": "freebsd irbt,s,ordered_insert/16384",
      "family_index": 0,
      "per_family_instance_index": 4,
      "run_name": "freebsd irbt,s,ordered_insert/16384",
      "run_type": "iteration",
      "repetitions": 1,
      "repetition_index": 0,
      "threads": 1,
      "iterations": 1503,
      "real_time": 4.7933286161014833e+05,
      "cpu_time": 4.7927236726546928e+05,
      "time_unit": "ns"
    },
    {
      "name": "freebsd irbt,s,ordered_insert/32768",
      "family_index": 0,
      "per_family_instance_index": 5,
      "run_name": "freebsd irbt,s,ordered_insert/32768",
      "run_type": "iteration",
      "repetitions": 1,
      "repetition_index": 0,
      "threads": 1,
      "iterations": 686,
      "real_time": 1.0120940743439086e+06,
      "cpu_time": 1.0120170860058301e+06,
      "time_unit": "ns"
    },
    {
      "name": "freebsd irbt,s,ordered_insert/65536",
      "family_index": 0,
      "per_family_instance_index": 6,
      "run_name": "freebsd irbt,s,ordered_insert/65536",
      "run_type": "iteration",
      "repetitions": 1,
      "repetition_index": 0,
      "threads": 1,
      "iterations": 305,
      "real_time": 2.2290081180322943e+06,
      "cpu_time": 2.2287583213114771e+06,
      "time_unit": "ns"
    },
    {
      "name": "freebsd irbt,s,ordered_insert/131072",
      "family_index": 0,
      "per_family_instance_index": 7,
      "run_name": "freebsd irbt,s,ordered_insert/131072",
      "run_type": "iteration",
      "repetitions": 1,
      "repetition_index": 0,
      "threads": 1,
      "iterations": 143,
      "real_time": 4.8885551958039179e+06,
      "cpu_time": 4.8876404335664297e+06,
      "time_unit": "ns"
    },
    {
      "name": "freebsd irbt,s,ordered_insert/262144",
      "family_index": 0,
      "per_family_instance_index": 8,
      "run_name": "freebsd irbt,s,ordered_insert/262144",
      "run_type": "iteration",
      "repetitions": 1,
      "repetition_index": 0,
      "threads": 1,
      "iterations": 46,
      "real_time": 1.5317717108700890e+07,
      "cpu_time": 1.5315244956521729e+07,
      "time_unit": "ns"
    },
    {
      "name": "freebsd irbt,s,ordered_insert/524288",
      "family_index": 0,
      "per_family_instance_index": 9,
      "run_name": "freebsd irbt,s,ordered_insert/524288",
      "run_type": "iteration",
      "repetitions": 1,
      "repetition_index": 0,
      "threads": 1,
      "iterations": 22,
      "real_time": 3.2804636818168961e+07,
      "cpu_time": 3.2797816681818176e+07,
      "time_unit": "ns"
    },
    {
      "name": "freebsd irbt,s,ordered_insert/1048576",
      "family_index": 0,
      "per_family_instance_index": 10,
      "run_name": "freebsd irbt,s,ordered_insert/1048576",
      "run_type": "iteration",
      "repetitions": 1,
      "repetition_index": 0,
      "threads": 1,
      "iterations": 7,
      "real_time": 1.0270890057147752e+08,
      "cpu_time": 1.0269514628571436e+08,
      "time_unit": "ns"
    },
    {
      "name": "freebsd irbt,s,ordered_insert/2097152",
      "family_index": 0,
      "per_family_instance_index": 11,
      "run_name": "freebsd irbt,s,ordered_insert/2097152",
      "run_type": "iteration",
      "repetitions": 1,
      "repetition_index": 0,
      "threads": 1,
      "iterations": 3,
      "real_time": 2.2699866100022820e+08,
      "cpu_time": 2.2694481566666684e+08,
      "time_unit": "ns"
    },
    {
      "name": "freebsd irbt,s,ordered_insert_BigO",
      "family_index": 0,
      "per_family_instance_index": 0,
      "run_name": "freebsd irbt,s,ordered_insert",
      "run_type": "aggregate",
      "repetitions": 1,
      "threads": 1,
      "aggregate_name": "BigO",
      "aggregate_unit": "time",
      "cpu_coefficient": 5.0100310073888599e+00,
      "real_coefficient": 5.0111245587711784e+00,
      "big_o": "NlgN",
      "time_unit": "ns"
    },
    {
      "name": "freebsd irbt,s,ordered_insert_RMS",
      "family_index": 0,
      "per_family_instance_index": 0,
      "run_name": "freebsd irbt,s,ordered_insert",
      "run_type": "aggregate",
      "repetitions": 1,
      "threads": 1,
      "aggregate_name": "RMS",
      "aggregate_unit": "percentage",
      "rms": 1.9182163831088891e-01
    },
    {
      "name": "linux irbt,o,ordered_insert/1024",
      "family_index": 1,
      "per_family_instance_index": 0,
      "run_name": "linux irbt,o,ordered_insert/1024",
      "run_type": "iteration",
      "repetitions": 1,
      "repetition_index": 0,
      "threads": 1,
      "iterations": 42889,
      "real_time": 1.6299236843946539e+04,
      "cpu_time": 1.6297839702487814e+04,
      "time_unit": "ns"
    },
    {
      "name": "linux irbt,o,ordered_insert/2048",
      "family_index": 1,
      "per_family_instance_index": 1,
      "run_name": "linux irbt,o,ordered_insert/2048",
      "run_type": "iteration",
      "repetitions": 1,
      "repetition_index": 0,
      "threads": 1,
      "iterations": 19283,
      "real_time": 3.7870082404192151e+04,
      "cpu_time": 3.7863106466836107e+04,
      "time_unit": "ns"
    },
    {
      "name": "linux irbt,o,ordered_insert/4096",
      "family_index": 1,
      "per_family_instance_index": 2,
      "run_name": "linux irbt,o,ordered_insert/4096",
      "run_type": "iteration",
      "repetitions": 1,
      "repetition_index": 0,
      "threads": 1,
      "iterations": 8686,
      "real_time": 8.0184723117627975e+04,
      "cpu_time": 8.0176745337324392e+04,
      "time_unit": "ns"
    },
    {
      "name": "linux irbt,o,ordered_insert/8192",
      "family_index": 1,
      "per_family_instance_index": 3,
      "run_name": "linux irbt,o,ordered_insert/8192",
      "run_type": "iteration",
      "repetitions": 1,
      "repetition_index": 0,
      "threads": 1,
      "iterations": 3988,
      "real_time": 1.7651578861564928e+05,
      "cpu_time": 1.7647783099297897e+05,
      "time_unit": "ns"
    },
    {
      "name": "linux irbt,o,ordered_insert/16384",
      "family_index": 1,
      "per_family_instance_index": 4,
      "run_name": "linux irbt,o,ordered_insert/16384",
      "run_type": "iteration",
      "repetitions": 1,
      "repetition_index": 0,
      "threads": 1,
      "iterations": 1570,
      "real_time": 4.4610482866269746e+05,
      "cpu_time": 4.4606486624203873e+05,
      "time_unit": "ns"
    },
    {
      "name": "linux irbt,o,ordered_insert/32768",
      "family_index": 1,
      "per_family_instance_index": 5,
      "run_name": "linux irbt,o,ordered_insert/32768",
      "run_type": "iteration",
      "repetitions": 1,
      "repetition_index": 0,
      "threads": 1,
      "iterations": 576,
      "real_time": 1.2194626128471480e+06,
      "cpu_time": 1.2194568211805571e+06,
      "time_unit": "ns"
    },
    {
      "name": "linux irbt,o,ordered_insert/65536",
      "family_index": 1,
      "per_family_instance_index": 6,
      "run_name": "linux irbt,o,ordered_insert/65536",
      "run_type": "iteration",
      "repetitions": 1,
      "repetition_index": 0,
      "threads": 1,
      "iterations": 215,
      "real_time": 3.3250773116251789e+06,
      "cpu_time": 3.3246818325581504e+06,
      "time_unit": "ns"
    },
    {
      "name": "linux irbt,o,ordered_insert/131072",
      "family_index": 1,
      "per_family_instance_index": 7,
      "run_name": "linux irbt,o,ordered_insert/131072",
      "run_type": "iteration",
      "repetitions": 1,
      "repetition_index": 0,
      "threads": 1,
      "iterations": 82,
      "real_time": 8.4626093170654941e+06,
      "cpu_time": 8.4615396097560953e+06,
      "time_unit": "ns"
    },
    {
      "name": "linux irbt,o,ordered_insert/262144",
      "family_index": 1,
      "per_family_instance_index": 8,
      "run_name": "linux irbt,o,ordered_insert/262144",
      "run_type": "iteration",
      "repetitions": 1,
      "repetition_index": 0,
      "threads": 1,
      "iterations": 33,
      "real_time": 2.0762695606070779e+07,
      "cpu_time": 2.0760413393939339e+07,
      "time_unit": "ns"
    },
    {
      "name": "linux irbt,o,ordered_insert/524288",
      "family_index": 1,
      "per_family_instance_index": 9,
      "run_name": "linux irbt,o,ordered_insert/524288",
      "run_type": "iteration",
      "repetitions": 1,
      "repetition_index": 0,
      "threads": 1,
      "iterations": 15,
      "real_time": 4.6396083200003587e+07,
      "cpu_time": 4.6391988999999970e+07,
      "time_unit": "ns"
    },
    {
      "name": "linux irbt,o,ordered_insert/1048576",
      "family_index": 1,
      "per_family_instance_index": 10,
      "run_name": "linux irbt,o,ordered_insert/1048576",
      "run_type": "iteration",
      "repetitions": 1,
      "repetition_index": 0,
      "threads": 1,
      "iterations": 7,
      "real_time": 1.0570850057138158e+08,
      "cpu_time": 1.0569040457142875e+08,
      "time_unit": "ns"
    },
    {
      "name": "linux irbt,o,ordered_insert/2097152",
      "family_index": 1,
      "per_family_instance_index": 11,
      "run_name": "linux irbt,o,ordered_insert/2097152",
      "run_type": "iteration",
      "repetitions": 1,
      "repetition_index": 0,
      "threads": 1,
      "iterations": 3,
      "real_time": 2.3876846033332792e+08,
      "cpu_time": 2.3870616733333349e+08,
      "time_unit": "ns"
    },
    {
      "name": "linux irbt,o,ordered_insert_BigO",
      "family_index": 1,
      "per_family_instance_index": 0,
      "run_name": "linux irbt,o,ordered_insert",
      "run_type": "aggregate",
      "repetitions": 1,
      "threads": 1,
      "aggregate_name": "BigO",
      "aggregate_unit": "time",
      "cpu_coefficient": 5.3096071362186184e+00,
      "real_coefficient": 5.3108743860206662e+00,
      "big_o": "NlgN",
      "time_unit": "ns"
    },
    {
      "name": "linux irbt,o,ordered_insert_RMS",
      "family_index": 1,
      "per_family_instance_index": 0,
      "run_name": "linux irbt,o,ordered_insert",
      "run_type": "aggregate",
      "repetitions": 1,
      "threads": 1,
      "aggregate_name": "RMS",
      "aggregate_unit": "percentage",
      "rms": 9.4822469886828423e-02
    },
    {
      "name": "iwavl,>,ordered_insert/1024",
      "family_index": 2,
      "per_family_instance_index": 0,
      "run_name": "iwavl,>,ordered_insert/1024",
      "run_type": "iteration",
      "repetitions": 1,
      "repetition_index": 0,
      "threads": 1,
      "iterations": 47781,
      "real_time": 1.5296429312903398e+04,
      "cpu_time": 1.5294881208011515e+04,
      "time_unit": "ns"
    },
    {
      "name": "iwavl,>,ordered_insert/2048",
      "family_index": 2,
      "per_family_instance_index": 1,
      "run_name": "iwavl,>,ordered_insert/2048",
      "run_type": "iteration",
      "repetitions": 1,
      "repetition_index": 0,
      "threads": 1,
      "iterations": 21810,
      "real_time": 3.2077217927534024e+04,
      "cpu_time": 3.2075849610270529e+04,
      "time_unit": "ns"
    },
    {
      "name": "iwavl,>,ordered_insert/4096",
      "family_index": 2,
      "per_family_instance_index": 2,
      "run_name": "iwavl,>,ordered_insert/4096",
      "run_type": "iteration",
      "repetitions": 1,
      "repetition_index": 0,
      "threads": 1,
      "iterations": 10091,
      "real_time": 6.8716277375888545e+04,
      "cpu_time": 6.8705689327122964e+04,
      "time_unit": "ns"
    },
    {
      "name": "iwavl,>,ordered_insert/8192",
      "family_index": 2,
      "per_family_instance_index": 3,
      "run_name": "iwavl,>,ordered_insert/8192",
      "run_type": "iteration",
      "repetitions": 1,
      "repetition_index": 0,
      "threads": 1,
      "iterations": 4690,
      "real_time": 1.5551491684447046e+05,
      "cpu_time": 1.5548991385927540e+05,
      "time_unit": "ns"
    },
    {
      "name": "iwavl,>,ordered_insert/16384",
      "family_index": 2,
      "per_family_instance_index": 4,
      "run_name": "iwavl,>,ordered_insert/16384",
      "run_type": "iteration",
      "repetitions": 1,
      "repetition_index": 0,
      "threads": 1,
      "iterations": 2079,
      "real_time": 3.1899606012465421e+05,
      "cpu_time": 3.1896910341510386e+05,
      "time_unit": "ns"
    },
    {
      "name": "iwavl,>,ordered_insert/32768",
      "family_index": 2,
      "per_family_instance_index": 5,
      "run_name": "iwavl,>,ordered_insert/32768",
      "run_type": "iteration",
      "repetitions": 1,
      "repetition_index": 0,
      "threads": 1,
      "iterations": 1028,
      "real_time": 7.2357780836576479e+05,
      "cpu_time": 7.2340051556420268e+05,
      "time_unit": "ns"
    },
    {
      "name": "iwavl,>,ordered_insert/65536",
      "family_index": 2,
      "per_family_instance_index": 6,
      "run_name": "iwavl,>,ordered_insert/65536",
      "run_type": "iteration",
      "repetitions": 1,
      "repetition_index": 0,
      "threads": 1,
      "iterations": 480,
      "real_time": 1.4532340645833605e+06,
      "cpu_time": 1.4531236541666621e+06,
      "time_unit": "ns"
    },
    {
      "name": "iwavl,>,ordered_insert/131072",
      "family_index": 2,
      "per_family_instance_index": 7,
      "run_name": "iwavl,>,ordered_insert/131072",
      "run_type": "iteration",
      "repetitions": 1,
      "repetition_index": 0,
      "threads": 1,
      "iterations": 219,
      "real_time": 3.2023089817322385e+06,
      "cpu_time": 3.2014823378995392e+06,
      "time_unit": "ns"
    },
    {
      "name": "iwavl,>,ordered_insert/262144",
      "family_index": 2,
      "per_family_instance_index": 8,
      "run_name": "iwavl,>,ordered_insert/262144",
      "run_type": "iteration",
      "repetitions": 1,
      "repetition_index": 0,
      "threads": 1,
      "iterations": 71,
      "real_time": 9.9442079295763951e+06,
      "cpu_time": 9.9426193943661936e+06,
      "time_unit": "ns"
    },
    {
      "name": "iwavl,>,ordered_insert/524288",
      "family_index": 2,
      "per_family_instance_index": 9,
      "run_name": "iwavl,>,ordered_insert/524288",
      "run_type": "iteration",
      "repetitions": 1,
      "repetition_index": 0,
      "threads": 1,
      "iterations": 26,
      "real_time": 2.6199274653838355e+07,
      "cpu_time": 2.6196780461538412e+07,
      "time_unit": "ns"
    },
    {
      "name": "iwavl,>,ordered_insert/1048576",
      "family_index": 2,
      "per_family_instance_index": 10,
      "run_name": "iwavl,>,ordered_insert/1048576",
      "run_type": "iteration",
      "repetitions": 1,
      "repetition_index": 0,
      "threads": 1,
      "iterations": 12,
      "real_time": 6.1585714666610628e+07,
      "cpu_time": 6.1572883000000186e+07,
      "time_unit": "ns"
    },
    {
      "name": "iwavl,>,ordered_insert/2097152",
      "family_index": 2,
      "per_family_instance_index": 11,
      "run_name": "iwavl,>,ordered_insert/2097152",
      "run_type": "iteration",
      "repetitions": 1,
      "repetition_index": 0,
      "threads": 1,
      "iterations": 5,
      "real_time": 1.3501401140001690e+08,
      "cpu_time": 1.3498462299999970e+08,
      "time_unit": "ns"
    },
    {
      "name": "iwavl,>,ordered_insert_BigO",
      "family_index": 2,
      "per_family_instance_index": 0,
      "run_name": "iwavl,>,ordered_insert",
      "run_type": "aggregate",
      "repetitions": 1,
      "threads": 1,
      "aggregate_name": "BigO",
      "aggregate_unit": "time",
      "cpu_coefficient": 3.0125116640467895e+00,
      "real_coefficient": 3.0131489320226579e+00,
      "big_o": "NlgN",
      "time_unit": "ns"
    },
    {
      "name": "iwavl,>,ordered_insert_RMS",
      "family_index": 2,
      "per_family_instance_index": 0,
      "run_name": "iwavl,>,ordered_insert",
      "run_type": "aggregate",
      "repetitions": 1,
      "threads": 1,
      "aggregate_name": "RMS",
      "aggregate_unit": "percentage",
      "rms": 1.0928569864641142e-01
    }
  ]
}
